os_sdk_light/__init__.py
os_sdk_light/client.py
os_sdk_light/exceptions.py
os_sdk_light/schemas/compute.yaml
os_sdk_light/schemas/image.yaml
os_sdk_light/schemas/network.yaml
os_sdk_light/schemas/placement.yaml
os_sdk_light/tests/__init__.py
os_sdk_light/tests/conftest.py
os_sdk_light/tests/test_common.py
os_sdk_light/tests/test_compute.py
os_sdk_light/tests/test_image.py
os_sdk_light/tests/test_network.py
os_sdk_light/tests/test_placement.py
os_sdk_light-0.2.7.dist-info/DESCRIPTION.rst
os_sdk_light-0.2.7.dist-info/METADATA
os_sdk_light-0.2.7.dist-info/RECORD
os_sdk_light-0.2.7.dist-info/WHEEL
os_sdk_light-0.2.7.dist-info/metadata.json
os_sdk_light-0.2.7.dist-info/top_level.txt
