Metadata-Version: 2.0
Name: os-sdk-light
Version: 0.2.7
Summary: Lightweight OpenStack client with schema based approach
Home-page: https://github.com/amadev/os-sdk-light
Author: Andrey Volkov
Author-email: amadev@mail.ru
License: MIT
Keywords: openstack client swagger openapi
Platform: UNKNOWN
Classifier: Development Status :: 3 - Alpha
Classifier: Environment :: Console
Classifier: Intended Audience :: Developers
Classifier: Intended Audience :: System Administrators
Classifier: License :: OSI Approved :: MIT License
Classifier: Operating System :: POSIX :: Linux
Classifier: Programming Language :: Python :: 3
Classifier: Topic :: Software Development :: Libraries
Classifier: Topic :: Utilities
Requires-Dist: bravado
Requires-Dist: os-client-config
